binanceSpotEasyT/__init__.py
binanceSpotEasyT/initialization.py
binanceSpotEasyT/rates.py
binanceSpotEasyT/tick.py
binanceSpotEasyT/timeframe.py
binanceSpotEasyT/trade.py
binanceSpotEasyT/util.py
tests/__init__.py
tests/conftest.py
tests/test_initialization.py
tests/test_rates.py
tests/test_tick.py
tests/test_trade.py
binanceSpotEasyT-0.0.5.dist-info/LICENSE
binanceSpotEasyT-0.0.5.dist-info/METADATA
binanceSpotEasyT-0.0.5.dist-info/WHEEL
binanceSpotEasyT-0.0.5.dist-info/top_level.txt
binanceSpotEasyT-0.0.5.dist-info/RECORD
