Metadata-Version: 2.1
Name: binanceSpotEasyT
Version: 0.0.5
Summary: UNKNOWN
Home-page: https://github.com/Joaopeuko/binanceSpotEasyT
Author: Joao Paulo Euko
License: MIT
Keywords: binance,spot,algotrading,cryptocurrency,automatic trade,automated trade
Platform: UNKNOWN
License-File: LICENSE
Requires-Dist: numpy
Requires-Dist: pandas
Requires-Dist: pytest
Requires-Dist: coverage
Requires-Dist: requests
Requires-Dist: pytest-cov
Requires-Dist: setuptools
Requires-Dist: abstractEasyT
Requires-Dist: python-dotenv
Requires-Dist: supportLibEasyT
